README.rst
setup.py
hplefthandclient/__init__.py
hplefthandclient/client.py
hplefthandclient/exceptions.py
hplefthandclient/http.py
hplefthandclient.egg-info/PKG-INFO
hplefthandclient.egg-info/SOURCES.txt
hplefthandclient.egg-info/dependency_links.txt
hplefthandclient.egg-info/requires.txt
hplefthandclient.egg-info/top_level.txt
test/test_HPLeftHandClient_Exception.py
test/test_HPLeftHandClient_base.py
test/test_HPLeftHandClient_server.py
test/test_HPLeftHandClient_system.py
test/test_HPLeftHandClient_volume.py